brainary/__init__.py
brainary/agents/__init__.py
brainary/agents/base_agent.py
brainary/agents/pok.py
brainary/control/__init__.py
brainary/control/flow.py
brainary/core/__init__.py
brainary/core/bus.py
brainary/core/context.py
brainary/core/errors.py
brainary/core/kernel.py
brainary/core/learning.py
brainary/core/metacognitive_kernel.py
brainary/core/metacognitive_monitor.py
brainary/core/metacognitive_rules.py
brainary/core/resource_manager.py
brainary/core/scheduler.py
brainary/domains/java_security/__init__.py
brainary/domains/java_security/agents.py
brainary/domains/java_security/detector.py
brainary/domains/java_security/knowledge.py
brainary/domains/java_security/primitives.py
brainary/domains/java_security/tools.py
brainary/domains/security/__init__.py
brainary/domains/security/cwe_database.py
brainary/domains/security/primitives.py
brainary/domains/security/vulnerability_detector.py
brainary/executors/__init__.py
brainary/executors/base.py
brainary/executors/direct_llm.py
brainary/executors/react_agent.py
brainary/llm/__init__.py
brainary/llm/config.py
brainary/llm/cost_tracker.py
brainary/llm/driver.py
brainary/llm/manager.py
brainary/llm/providers.py
brainary/memory/__init__.py
brainary/memory/associative.py
brainary/memory/attention.py
brainary/memory/episodic.py
brainary/memory/manager.py
brainary/memory/semantic.py
brainary/memory/working.py
brainary/plugin/__init__.py
brainary/plugin/base.py
brainary/plugin/loader.py
brainary/plugin/registry.py
brainary/primitive/__init__.py
brainary/primitive/base.py
brainary/primitive/catalog.py
brainary/primitive/registry.py
brainary/primitive/router.py
brainary/primitive/implementations/__init__.py
brainary/primitive/implementations/composite/__init__.py
brainary/primitive/implementations/composite/analyze.py
brainary/primitive/implementations/composite/create.py
brainary/primitive/implementations/composite/decide.py
brainary/primitive/implementations/composite/decompose.py
brainary-0.1.3.dist-info/METADATA
brainary-0.1.3.dist-info/WHEEL
brainary-0.1.3.dist-info/top_level.txt
brainary-0.1.3.dist-info/RECORD
