Metadata-Version: 2.4
Name: brainary
Version: 0.1.3
Summary: A cognitive computing platform for AI development
Home-page: https://github.com/cs-wangchong/Brainary
Author: NTU Brainary Team
Author-email: Brainary Team <team@brainary.ai>
License: MIT
Project-URL: Homepage, https://github.com/cs-wangchong/brainary
Project-URL: Repository, https://github.com/cs-wangchong/brainary
Project-URL: Documentation, https://brainary.readthedocs.io
Project-URL: Issues, https://github.com/cs-wangchong/brainary/issues
Classifier: Development Status :: 4 - Beta
Classifier: Intended Audience :: Developers
Classifier: License :: OSI Approved :: MIT License
Classifier: Programming Language :: Python :: 3
Classifier: Programming Language :: Python :: 3.8
Classifier: Programming Language :: Python :: 3.9
Classifier: Programming Language :: Python :: 3.10
Classifier: Programming Language :: Python :: 3.11
Classifier: Topic :: Scientific/Engineering :: Artificial Intelligence
Classifier: Topic :: Software Development :: Libraries :: Python Modules
Requires-Python: >=3.8
Requires-Dist: openai>=1.3.0
Requires-Dist: pydantic>=2.0.0
Requires-Dist: numpy>=1.21.0
Requires-Dist: tqdm>=4.64.0
Requires-Dist: python-dotenv>=0.19.0
Requires-Dist: aiofiles>=0.8.0
Requires-Dist: asyncio-extras>=1.3.0
Provides-Extra: dev
Requires-Dist: pytest>=6.0; extra == "dev"
Requires-Dist: pytest-asyncio>=0.18.0; extra == "dev"
Requires-Dist: black>=22.0.0; extra == "dev"
Requires-Dist: isort>=5.10.0; extra == "dev"
Requires-Dist: mypy>=0.950; extra == "dev"
